{"multi - cellular organism": ["anatomical structure"], "prosoma": ["tagma"], "opisthosoma": ["tagma"], "cuticle": ["acellular anatomical structure"], "carapace": ["sclerite"], "pedicel": ["opisthosomal segment 1"], "portion of organism substance": ["material anatomical entity"], "spinneret": ["appendage"], "tagma": ["organism subdivision"], "eye": ["sensory  organ"], "chelicera": ["appendage"], "female palp": ["palp"], "leg 1": ["leg"], "leg 2": ["leg"], "leg 3": ["leg"], "leg 4": ["leg"], "pedicel sternite": ["opisthosomal sternite"], "pedicel tergite": ["opisthosomal tergite"], "anterior booklung": ["booklung"], "anterior lateral spinneret": ["spinneret"], "posterior median spinneret": ["spinneret"], "posterior lateral spinneret": ["spinneret"], "chilum": ["sclerite"], "anal tubercle tergite": ["opisthosomal tergite"], "anal tubercle sternite": ["opisthosomal sternite"], "integument": ["anatomical system"], "female genitalia": ["anatomical cluster"], "male palp": ["palp"], "anterior median eye": ["direct eye"], "anterior lateral eye": ["eye"], "posterior median eye": ["eye"], "posterior lateral eye": ["eye"], "silk cable": ["silk structure"], "silk fiber": ["silk structure"], "opisthosomal segment": ["segment"], "posterior booklung": ["booklung"], "clypeal gland": ["gland", "depression"], "suprapalpal pit gland": ["gland", "depression"], "median trachea": ["trachea", "posterior respiratory system"], "entapophysis 3": ["opisthosomal entapophysis"], "fang": ["podomere"], "paturon": ["podomere"], "posterior booklung spiracle": ["booklung spiracle"], "posterior booklung leaf": ["booklung leaf"], "intercheliceral sclerite": ["sclerite"], "female palpal coxa": ["podomere"], "female palpal trochanter": ["podomere"], "female palpal femur": ["podomere"], "female palpal patella": ["podomere"], "female palpal tibia": ["podomere"], "female palpal tarsus": ["podomere"], "palpal claw": ["claw"], "anterior median spinneret": ["spinneret"], "coxa 1": ["coxa"], "trochanter 1": ["trochanter"], "femur 1": ["femur"], "patella 1": ["patella"], "tibia 1": ["tibia"], "metatarsus 1": ["metatarsus"], "tarsus 1": ["tarsus"], "claw 1": ["claw"], "coxa 2": ["coxa"], "trochanter 2": ["trochanter"], "femur 2": ["femur"], "patella 2": ["patella"], "tibia 2": ["tibia"], "metatarsus 2": ["metatarsus"], "tarsus 2": ["tarsus"], "claw 2": ["claw"], "coxa 3": ["coxa"], "trochanter 3": ["trochanter"], "femur 3": ["femur"], "patella 3": ["patella"], "tibia 3": ["tibia"], "metatarsus 3": ["metatarsus"], "tarsus 3": ["tarsus"], "claw 3": ["claw"], "coxa 4": ["coxa"], "trochanter 4": ["trochanter"], "femur 4": ["femur"], "patella 4": ["patella"], "tibia 4": ["tibia"], "metatarsus 4": ["metatarsus"], "tarsus 4": ["tarsus"], "claw 4": ["claw"], "foregut": ["integumental tube"], "coxal gland": ["gland"], "spigot of anterior median spinneret": ["anterior median spinneret"], "lateral trachea": ["trachea", "posterior respiratory system"], "spinning field of anterior lateral spinneret": ["spinning field"], "spinning field of posterior median spinneret": ["spinning field"], "spinning field of posterior lateral spinneret": ["spinning field"], "heart": ["epithelial tube"], "anterior copulatory duct": ["copulatory duct"], "copulatory opening": ["anatomical space"], "anterior fertilization duct": ["fertilization duct"], "bennett's gland": ["cluster of glandular units"], "epigynal cuticular glands": ["gland"], "male palpal coxa": ["podomere"], "male palpal trochanter": ["podomere"], "male palpal femur": ["podomere"], "male palpal patella": ["podomere"], "male palpal tibia": ["podomere"], "male palpal tibia dorsal process": ["male palpal tibial process"], "male palpal tibia prolateral process": ["male palpal tibial process"], "male palpal tibia retrolateral apophysis": ["male palpal tibial process"], "male palpal tibia ventral process": ["male palpal tibial process"], "cymbium": ["podomere"], "tarsal organ of cymbium": ["tarsal organ"], "base of major ampullate gland spigot": ["spigot base"], "cymbium dorsal chemosensory seta": ["seta of cymbium", "chemosensory seta"], "cymbium apical seta": ["seta of cymbium"], "paracymbium": ["process of cymbium"], "cymbial dorsal process": ["process of cymbium"], "basal hematodocha": ["hematodocha"], "subtegulum": ["sclerite"], "tegulum": ["sclerite"], "median hematodocha": ["hematodocha"], "embolic division": ["division of copulatory bulb"], "embolus": ["sclerite"], "spermophor": ["integumental tube"], "median apophysis": ["sclerite"], "conductor": ["sclerite"], "terminal hematodocha": ["hematodocha"], "shaft of major ampullate gland spigot": ["spigot shaft"], "base of piriform gland spigot": ["spigot base"], "cheliceral gland": ["gland"], "cheliceral stridulatory file": ["stridulatory file"], "shaft of piriform gland spigot": ["spigot shaft"], "shaft of aciniform gland spigot of posterior lateral spinneret": ["spigot shaft"], "anterior median eye retina": ["retina"], "anterior lateral eye tapetum": ["tapetum"], "posterior median eye tapetum": ["tapetum"], "posterior lateral eye tapetum": ["tapetum"], "maxillary gland": ["gland"], "base of aciniform gland spigot of posterior lateral spinneret": ["spigot base"], "female palpal tarsus dorsal chemosensory seta": ["chemosensory seta"], "retrocoxal hymen 1": ["retrocoxal hymen"], "base of cylindrical gland spigot of posterior lateral spinneret": ["spigot base"], "shaft of cylindrical gland spigot of posterior lateral spinneret": ["spigot shaft"], "shaft of modified gland spigot of posterior lateral spinneret": ["spigot shaft"], "base of modified gland spigot of posterior lateral spinneret": ["spigot base"], "base of paracribellar gland spigot of posterior lateral spinneret": ["spigot base"], "shaft of paracribellar gland spigot of posterior lateral spinneret": ["spigot shaft"], "shaft of gland spigot of posterior lateral spinneret": ["spigot shaft"], "base of gland spigot of posterior lateral spinneret": ["spigot base"], "aggregate gland spigot": ["spigot of posterior lateral spinneret", "spigot"], "scopular seta": ["tenent seta"], "socket of scopular seta": ["setal socket"], "tenent barb of scopular seta": ["tenent barb"], "claw tuft seta": ["tenent seta"], "tenent barb of claw tuft seta": ["tenent barb"], "proclaw 1": ["superior claw 1", "proclaw"], "retroclaw 1": ["retroclaw", "superior claw 1"], "inferior claw 1": ["inferior claw", "claw 1"], "proclaw 2": ["proclaw", "superior claw 2"], "retroclaw 2": ["retroclaw", "superior claw 2"], "inferior claw 2": ["claw 2", "inferior claw"], "proclaw 3": ["proclaw", "superior claw 3"], "retroclaw 3": ["retroclaw", "superior claw 3"], "inferior claw 3": ["inferior claw", "claw 3"], "proclaw 4": ["proclaw", "superior claw 4"], "retroclaw 4": ["retroclaw", "superior claw 4"], "inferior claw 4": ["claw 4", "inferior claw"], "calamistrum": ["cluster of setae"], "calamistrum seta": ["seta"], "tarsal setal comb 4": ["cluster of setae"], "female palp femoral thorn": ["palpal femoral thorn"], "lyra": ["stridulatory organ"], "base of aciniform gland spigot of posterior median spinneret": ["spigot base"], "shaft of aciniform gland spigot of posterior median spinneret": ["spigot shaft"], "base of cylindrical gland spigot of posterior median spinneret": ["spigot base", "base of cylindrical gland spigot"], "anterior booklung leaf": ["booklung leaf"], "shaft of cylindrical gland spigot of posterior median spinneret": ["spigot shaft"], "major ampullate gland spigot": ["spigot of anterior lateral spinneret", "ampullate gland spigot"], "sensillum of major ampullate field": ["strain sensillum of cuticle"], "piriform gland spigot": ["spigot of anterior lateral spinneret", "spigot"], "spigot of posterior median spinneret": ["spigot"], "minor ampullate gland spigot": ["ampullate gland spigot", "spigot of posterior median spinneret"], "aciniform gland spigot of posterior median spinneret": ["aciniform gland spigot", "spigot of posterior median spinneret"], "cylindrical gland spigot of posterior median spinneret": ["cylindrical gland spigot", "spigot of posterior median spinneret"], "aciniform gland spigot of posterior lateral spinneret": ["spigot of posterior lateral spinneret", "aciniform gland spigot"], "cylindrical gland spigot of posterior lateral spinneret": ["cylindrical gland spigot", "spigot of posterior lateral spinneret"], "modified gland spigot of posterior lateral spinneret": ["spigot of posterior lateral spinneret"], "paracribellar gland spigot of posterior lateral spinneret": ["paracribellar gland spigot", "spigot of posterior lateral spinneret"], "paracribellar gland spigot of posterior median spinneret": ["paracribellar gland spigot", "spigot of posterior median spinneret"], "sperm outlet": ["anatomical space"], "male palpal femoral thorn": ["palpal femoral thorn"], "socket of male palpal femoral thorn": ["setal socket"], "base of minor ampullate gland spigot": ["spigot base"], "shaft of minor ampullate gland spigot of posterior median spinneret": ["spigot shaft"], "cribellar spigot": ["spigot"], "spigot of posterior lateral spinneret": ["spigot"], "base of paracribellar gland spigot of posterior median spinneret": ["spigot base"], "shaft of paracribellar gland spigot of posterior median spinneret": ["spigot shaft"], "epigastric furrow posterior apodeme": ["apodeme"], "chemosensory seta": ["seta", "sensory  organ"], "labral tongue": ["sclerite"], "labial sigilla": ["sigilla"], "sternum": ["sclerite"], "sternal sigilla": ["sigilla"], "base of gland spigot of posterior median spinneret": ["spigot base"], "shaft of gland spigot of posterior median spinneret": ["spigot shaft"], "base of aggregate gland spigot": ["spigot base"], "shaft of aggregate gland spigot": ["spigot shaft"], "superior claw 1": ["claw 1", "superior claw"], "vertical intercoxal bar": ["sclerite"], "pleural bar": ["sclerite"], "maxillary cusple": ["cusple"], "opisthosomal dorsal sigilla": ["sigilla"], "tarsal organ": ["sensory  organ"], "scopula": ["cluster of setae"], "claw tuft": ["cluster of setae"], "trichobothria": ["seta", "sensory  organ"], "superior claw 2": ["claw 2", "superior claw"], "macroseta": ["seta", "sensory  organ"], "cymbial retrolateral - medial process": ["process of cymbium"], "silk structure": ["portion of organism substance"], "dragline": ["silk cable"], "sticky composed line": ["silk cable"], "egg": ["female germ cell", "gamete"], "anterior booklung spiracle": ["booklung spiracle"], "venom gland": ["gland"], "superior claw 3": ["claw 3", "superior claw"], "superior claw 4": ["claw 4", "superior claw"], "palp": ["appendage"], "indirect eye": ["eye"], "postembryo": ["multi - cellular organism"], "cusple": ["macroseta"], "bothrium": ["setal socket"], "trichobothria shaft": ["setal shaft"], "socket of macroseta": ["setal socket"], "tibial gland": ["gland"], "opisthosomal tergite": ["sclerite"], "opisthosomal sternite": ["sclerite"], "urticating hair": ["seta"], "aciniform gland spigot": ["spigot"], "pumpkiniform spigot": ["spigot"], "cylindrical gland spigot": ["spigot"], "ampullate gland spigot": ["spigot"], "paracribellar gland spigot": ["spigot"], "scopular seta shaft": ["setal shaft"], "leg": ["appendage"], "coxa": ["podomere", "leg article"], "trochanter": ["podomere", "leg article"], "femur": ["podomere", "leg article"], "patella": ["podomere", "leg article"], "tibia": ["podomere", "leg article"], "metatarsus": ["pseudopodomere", "leg article"], "tarsus": ["pseudopodomere", "leg article"], "podotarsite": ["tarsal pseudosegment"], "claw": ["acellular anatomical structure"], "superior claw": ["claw"], "proclaw": ["superior claw"], "retroclaw": ["superior claw"], "inferior claw": ["claw"], "direct eye": ["eye"], "anterior median eye lens": ["eye lens"], "anterior lateral eye lens": ["eye lens"], "posterior lateral eye lens": ["eye lens"], "posterior median eye lens": ["eye lens"], "tactile hair": ["seta", "sensory  organ"], "scale": ["seta"], "labial cusple": ["cusple"], "ac silk fiber": ["silk fiber"], "maamp silk fiber": ["silk fiber"], "miamp silk fiber": ["silk fiber"], "pc silk fiber": ["silk fiber"], "ms silk fiber": ["silk fiber"], "cy silk fiber": ["silk fiber"], "pi silk fiber": ["silk fiber"], "cribellar silk fiber": ["silk fiber"], "flagelliform gland spigot": ["modified gland spigot of posterior lateral spinneret", "spigot"], "pseudoflagelliform gland spigot": ["modified gland spigot of posterior lateral spinneret", "spigot"], "base of flagelliform gland spigot": ["base of modified gland spigot of posterior lateral spinneret"], "shaft of flagelliform gland spigot": ["shaft of modified gland spigot of posterior lateral spinneret"], "base of pseudoflagelliform gland spigot": ["base of modified gland spigot of posterior lateral spinneret"], "shaft of pseudoflagelliform gland spigot": ["shaft of modified gland spigot of posterior lateral spinneret"], "opisthosomal segment 1": ["opisthosomal segment"], "opisthosomal segment 2": ["opisthosomal segment"], "opisthosomal segment 3": ["opisthosomal segment"], "opisthosomal segment 4": ["opisthosomal segment"], "opisthosomal segment 5": ["opisthosomal segment"], "booklung spiracle": ["spiracle"], "posterior booklung atrium": ["booklung atrium"], "anterior booklung atrium": ["booklung atrium"], "trachea": ["integumental tube"], "tracheal spiracle": ["spiracle"], "opisthosomal entapophysis": ["apodeme"], "epigastric median trachea": ["trachea", "anterior respiratory system"], "pretarsus": ["podomere", "leg article"], "leg article": ["article"], "pretarsus 1": ["pretarsus"], "pretarsus 2": ["pretarsus"], "pretarsus 3": ["pretarsus"], "pretarsus 4": ["pretarsus"], "acellular anatomical structure": ["anatomical structure"], "plagula ventralis": ["sclerite"], "claw tuft seta shaft": ["setal shaft"], "socket of claw tuft seta": ["setal socket"], "cuticle sculpture cell": ["cuticular structure"], "claw lever 1": ["claw lever"], "claw lever 2": ["claw lever"], "claw lever 3": ["claw lever"], "claw lever 4": ["claw lever"], "promarginal escort seta": ["cheliceral escort seta"], "retromarginal escort seta": ["cheliceral escort seta"], "palpal pretarsus": ["podomere"], "slit sensillum": ["strain sensillum of cuticle"], "coxal muscle sclerite": ["coxa", "sclerite"], "coxal hair plate": ["sensory  organ", "cluster of setae"], "lyriform organ": ["sensory  organ"], "vibration sense organ": ["lyriform organ"], "foot slit": ["slit sensillum"], "elongated pedicillate seta": ["seta", "sensory  organ"], "tenent barb": ["setal barb"], "tenent seta": ["seta"], "female palpal chemosensory patch": ["cluster of setae"], "cymbial chemosensory patch": ["cluster of setae"], "pseudotenent seta": ["tenent seta"], "scale shaft": ["setal shaft"], "socket of scale": ["setal socket"], "socket of chemosensory seta": ["setal socket"], "booklung atrium mesh": ["anterior booklung atrium"], "interpulmonary fold": ["anterior respiratory system"], "apodeme": ["cuticular structure"], "tracheole": ["trachea"], "entapophysis 2": ["opisthosomal entapophysis"], "entapophysis 4": ["opisthosomal entapophysis"], "entapophysis 5": ["opisthosomal entapophysis"], "strain sensillum of cuticle": ["sensory  organ"], "spigot end piece": ["spigot shaft"], "opisthosomal segment 11": ["opisthosomal segment"], "cuticular sheet of chemosensory seta": ["chemosensory seta shaft"], "basal division of copulatory bulb": ["division of copulatory bulb"], "median division of copulatory bulb": ["division of copulatory bulb"], "radix": ["sclerite"], "process of cymbium": ["process"], "male palpal tibial process": ["process"], "male palpal ventral - medial process": ["male palpal femoral process"], "male palpal ventral - basal process": ["male palpal femoral process"], "male palpal ventral - apical process": ["male palpal femoral process"], "male palpal patella dorsal process": ["male palpal patellar process"], "male palpal patella retrolateral process": ["male palpal patellar process"], "gland of male palpal tibia": ["gland"], "apical cymbial groove": ["groove of cymbium"], "retrolateral cymbial groove": ["groove of cymbium"], "male palpal tibia dorsal basal process": ["male palpal tibia dorsal process"], "male palpal tibia ventral apical process": ["male palpal tibia ventral process"], "anterior spermatheca": ["spermatheca"], "mating plug": ["portion of organism substance"], "gland of posterior diverticulum": ["gland", "female accessory gland"], "gland of spermatheca": ["gland", "female accessory gland"], "female accessory gland": ["gland"], "gland of accessory bulb": ["female accessory gland"], "spinning field of cribellum": ["spinning field"], "cheliceral whisker seta": ["seta"], "cheliceral escort seta": ["cheliceral whisker seta"], "anterior median eye cup": ["eye cup"], "anterior lateral eye cup": ["eye cup"], "shaft of aciniform gland spigot": ["spigot shaft"], "base of aciniform gland spigot": ["spigot base"], "gonopore": ["anatomical space"], "eggsac": ["silk structure"], "posterior lateral eye cup": ["eye cup"], "posterior median eye cup": ["eye cup"], "pedicel slit sensillum": ["slit sensillum"], "reproductive system": ["anatomical system"], "male reproductive system": ["reproductive system"], "female reproductive system": ["reproductive system"], "testis": ["gonad"], "deferent duct": ["epithelial tube"], "uterus": ["epithelial tube"], "ovary": ["gonad"], "male genitalia": ["anatomical cluster"], "posterior spermatheca": ["spermatheca"], "posterior fertilization duct": ["fertilization duct"], "posterior copulatory duct": ["copulatory duct"], "epigynal scape": ["process"], "gland of copulatory duct": ["female accessory gland"], "gland of fertilization duct": ["gland", "female accessory gland"], "cluster of glandular units": ["gland of spermatheca"], "peg tooth": ["macroseta"], "heart ostium 1": ["heart ostium"], "heart ostium 2": ["heart ostium"], "heart ostium 3": ["heart ostium"], "heart ostium 4": ["heart ostium"], "heart ostium 5": ["heart ostium"], "preying web": ["silk structure"], "digestive system": ["anatomical system"], "circulatory system": ["anatomical system"], "respiratory system": ["anatomical system"], "nervous system": ["anatomical system"], "malpighian tubule": ["epithelial tube"], "midgut": ["epithelial tube"], "silk gland": ["gland"], "excretory system": ["anatomical system"], "spinning apparatus": ["anatomical system"], "major ampullate gland": ["silk gland"], "piriform gland": ["silk gland"], "aciniform gland": ["silk gland"], "cylindrical gland": ["silk gland"], "flagelliform gland": ["silk gland"], "aggregate gland": ["silk gland"], "palpal femoral thorn": ["plectrum", "seta"], "serrate accessory claw seta": ["seta"], "sensory  organ": ["peripheral nervous system"], "appendage": ["organism subdivision"], "claw tuft clasper": ["superior claw"], "metatarsal preening comb": ["cluster of setae"], "leg cusple": ["cusple"], "tarsal organ of female palp": ["tarsal organ"], "tarsal organ of leg": ["tarsal organ"], "adult": ["multi - cellular organism"], "muscular system": ["anatomical system"], "muscle": ["portion of tissue"], "tendon": ["portion of tissue"], "article": ["sclerite"], "joint": ["anatomical cluster"], "eudesmatic joint": ["joint"], "adesmatic joint": ["joint"], "mouthparts": ["prosoma"], "material anatomical entity": ["anatomical entity"], "anatomical structure": ["material anatomical entity"], "anatomical group": ["anatomical structure"], "anatomical cluster": ["anatomical group"], "anatomical system": ["anatomical group"], "gland": ["anatomical cluster"], "spermophor gland": ["gland"], "bulb gland": ["gland"], "stridulatory organ": ["anatomical cluster"], "segment": ["anatomical cluster"], "organism subdivision": ["anatomical structure"], "portion of tissue": ["anatomical structure"], "immaterial anatomical entity": ["anatomical entity"], "anatomical space": ["immaterial anatomical entity"], "cheliceral diastema": ["anatomical space"], "cheliceral tooth": ["process"], "cheliceral lamina": ["process"], "rastellum": ["cluster of setae"], "palpal muscle m30": ["muscle"], "palpal muscle m29": ["muscle"], "fertilization duct": ["integumental tube"], "copulatory duct": ["integumental tube"], "procursus": ["process of cymbium"], "fulcrum": ["process"], "stipes": ["sclerite"], "paramedian apophysis": ["sclerite"], "sulcus": ["depression"], "minor ampullate gland": ["silk gland"], "paracribellar gland": ["silk gland"], "cribellar gland": ["silk gland"], "pseudoflagelliform gland": ["silk gland"], "pumpkiniform gland": ["silk gland"], "gonad": ["compound organ"], "compound organ": ["anatomical structure"], "seminal fluid": ["portion of tissue"], "cell": ["anatomical structure"], "sperm": ["male germ cell", "gamete"], "spermatid": ["male germ cell"], "spermatocyte": ["male germ cell"], "spermatogonium": ["male germ cell"], "somatic cell": ["cell"], "organelle": ["cell component"], "membrane - bounded organelle": ["organelle"], "non - membrane - bounded organelle": ["organelle"], "cytoplasmic vesicle": ["cytoplasmic part", "vesicle"], "secretory granule": ["cytoplasmic vesicle", "membrane - bounded organelle"], "acrosomal vacuole": ["secretory granule"], "vesicle": ["organelle"], "subacrosomal space": ["anatomical space"], "acrosomal complex": ["cell component"], "germ cell": ["cell"], "acrosomal filament": ["cytoskeletal part"], "cytoskeleton": ["cell component", "non - membrane - bounded organelle"], "male germ cell": ["germ cell"], "female germ cell": ["germ cell"], "gamete": ["germ cell"], "muscle cell": ["somatic cell"], "somatic cell of testis": ["somatic cell"], "hemocyte": ["somatic cell"], "syncytium": ["cell"], "axoneme": ["cytoskeletal part"], "mitochondrion": ["membrane - bounded organelle"], "nucleus": ["membrane - bounded organelle"], "sperm nucleus": ["nucleus"], "anterior indentation of the sperm nucleus": ["anatomical space"], "centriole": ["cytoskeletal part"], "manchette of microtubules": ["cytoskeletal part"], "midpiece": ["membrane - bounded organelle"], "nuclear canal": ["anatomical space"], "golgi apparatus": ["membrane - bounded organelle"], "endoplasmic reticulum": ["membrane - bounded organelle"], "sperm conjugate": ["sperm transfer form", "anatomical cluster"], "coenospermium": ["secondary sperm conjugate"], "rouleau": ["secondary sperm conjugate"], "primary sperm conjugate": ["sperm conjugate"], "secondary sperm conjugate": ["sperm conjugate"], "synspermium": ["primary sperm conjugate", "syncytium"], "seminal secretion": ["portion of organism substance"], "cleistospermium": ["sperm transfer form"], "oocyte": ["female germ cell"], "oogonial cell": ["female germ cell"], "oviduct": ["epithelial tube"], "hindgut": ["integumental tube"], "epithelium": ["portion of tissue"], "anatomical conduit": ["anatomical cluster"], "tube": ["anatomical conduit"], "epithelial tube": ["tube"], "epidermis": ["epithelium"], "socket of tactile hair": ["setal socket"], "integumental tube": ["tube"], "midgut gland": ["gland"], "embryonic cell": ["cell"], "early embryonic cell": ["embryonic cell"], "zygote": ["early embryonic cell"], "embryo": ["multi - cellular organism"], "immature": ["multi - cellular organism"], "penultimate": ["multi - cellular organism"], "implantation fossa": ["anatomical space"], "chromosome": ["non - membrane - bounded organelle"], "chromatin": ["chromosomal part"], "microtubule": ["cytoskeletal part"], "glycogen granule": ["cytoplasmic part"], "neural cell": ["somatic cell"], "neuron": ["neural cell"], "afferent neuron": ["neuron"], "efferent neuron": ["neuron"], "sensory neuron": ["afferent neuron"], "motor neuron": ["efferent neuron"], "interneuron": ["neuron"], "mechanoreceptor cell": ["sensory neuron"], "chemoreceptor cell": ["sensory neuron"], "secretory cell": ["somatic cell"], "exocrine cell": ["secretory cell"], "excretory cell": ["somatic cell"], "dorso - ventral abdominal muscle 1": ["muscle"], "dorso - ventral abdominal muscle 2": ["muscle"], "dorso - ventral abdominal muscle 3": ["muscle"], "dorso - ventral abdominal muscle 4": ["muscle"], "pretarsal levator leg muscle": ["muscle"], "pretarsal depressor leg muscle": ["muscle"], "pretarsal depressor leg tendon": ["tendon"], "pretarsal levator leg tendon": ["tendon"], "articular membrane": ["conjunctiva"], "condyle": ["articular surface"], "acetabulum": ["articular surface"], "articular surface": ["cuticular structure"], "podomere": ["article"], "pseudopodomere": ["article"], "pretarsal median septum": ["cuticular structure"], "pretarsal dorsal pulley": ["cuticular structure"], "levator cuticular guide": ["cuticular structure"], "depressor cuticular guide": ["cuticular structure"], "pretarsal ventral pulley": ["cuticular structure"], "levator sheath": ["cuticular structure"], "depressor sheath": ["cuticular structure"]}